test_stratergy/__init__.py
test_stratergy/testing.py
test_stratergy-0.0.3.dist-info/LICENSE
test_stratergy-0.0.3.dist-info/METADATA
test_stratergy-0.0.3.dist-info/WHEEL
test_stratergy-0.0.3.dist-info/top_level.txt
test_stratergy-0.0.3.dist-info/RECORD
