Metadata-Version: 2.1
Name: test-stratergy
Version: 0.0.3
Summary: This package is used to test you trading stragey integrated with deep learning models
Home-page: https://github.com/9harshit/trading_stratergy_package
Author: Harshit Agarwal
Author-email: 9arshit@gmail.com
License: UNKNOWN
Platform: UNKNOWN
Classifier: Programming Language :: Python :: 3
Classifier: License :: OSI Approved :: MIT License
Classifier: Operating System :: OS Independent
Requires-Python: >=3.6
